stravalib/__init__.py
stravalib/_version_generated.py
stravalib/client.py
stravalib/exc.py
stravalib/model.py
stravalib/protocol.py
stravalib/py.typed
stravalib/strava_model.py
stravalib/unit_helper.py
stravalib/unit_registry.py
stravalib/tests/__init__.py
stravalib/tests/auth_responder.py
stravalib/tests/conftest.py
stravalib/tests/test.ini-example
stravalib/tests/integration/__init__.py
stravalib/tests/integration/strava_api_stub.py
stravalib/tests/integration/test_client.py
stravalib/tests/resources/activity-manual.3.json
stravalib/tests/resources/activity.3.json
stravalib/tests/resources/athlete.2.json
stravalib/tests/resources/athlete.3.json
stravalib/tests/resources/example_route_response.json
stravalib/tests/resources/example_zone_response.json
stravalib/tests/resources/sample.tcx
stravalib/tests/resources/strava_swagger.json
stravalib/tests/unit/__init__.py
stravalib/tests/unit/test_client_utils.py
stravalib/tests/unit/test_limiter.py
stravalib/tests/unit/test_model.py
stravalib/tests/unit/test_unithelper.py
stravalib/tests/unit/test_validate_activity_type.py
stravalib/util/__init__.py
stravalib/util/limiter.py
stravalib-2.1.dist-info/LICENSE.txt
stravalib-2.1.dist-info/METADATA
stravalib-2.1.dist-info/WHEEL
stravalib-2.1.dist-info/top_level.txt
stravalib-2.1.dist-info/RECORD
