Metadata-Version: 2.1
Name: stravalib
Version: 2.1
Summary: A Python package that makes it easy to access and download data from the Strava V3 REST API.
Author-email: Hans Lellelid <hans@xmpl.org>
Maintainer: Leah Wasser, Hans Lellelid, Jonatan Samoocha, Yihong, Émile Nadeau
License: Apache 2.0 License
Project-URL: documentation, https://stravalib.readthedocs.io
Project-URL: repository, https://github.com/stravalib/stravalib
Project-URL: changelog, https://github.com/stravalib/stravalib/blob/main/changelog.md
Keywords: strava,running,cycling,athletes
Classifier: Development Status :: 5 - Production/Stable
Classifier: Programming Language :: Python
Classifier: Intended Audience :: Science/Research
Classifier: Intended Audience :: Developers
Classifier: License :: OSI Approved :: Apache Software License
Classifier: Natural Language :: English
Classifier: Operating System :: OS Independent
Classifier: Topic :: Scientific/Engineering
Classifier: Topic :: Software Development :: Libraries
Classifier: Programming Language :: Python :: 3 :: Only
Classifier: Programming Language :: Python :: 3.10
Classifier: Programming Language :: Python :: 3.11
Classifier: Programming Language :: Python :: 3.12
Requires-Python: >=3.10
License-File: LICENSE.txt
Requires-Dist: pint
Requires-Dist: pytz
Requires-Dist: arrow
Requires-Dist: requests
Requires-Dist: pydantic>=2.0
Provides-Extra: build
Requires-Dist: build; extra == "build"
Provides-Extra: tests
Requires-Dist: pytest; extra == "tests"
Requires-Dist: pytest-cov; extra == "tests"
Requires-Dist: responses; extra == "tests"
Provides-Extra: docs
Requires-Dist: sphinx; extra == "docs"
Requires-Dist: pydata-sphinx-theme; extra == "docs"
Requires-Dist: autodoc_pydantic; extra == "docs"
Requires-Dist: sphinx_remove_toctrees; extra == "docs"
Requires-Dist: myst-nb; extra == "docs"
Requires-Dist: sphinx-autobuild; extra == "docs"
Requires-Dist: sphinx-inline-tabs; extra == "docs"
Requires-Dist: sphinx_copybutton; extra == "docs"
Requires-Dist: sphinx_design; extra == "docs"
Requires-Dist: sphinxext-opengraph; extra == "docs"
Requires-Dist: matplotlib; extra == "docs"
Requires-Dist: sphinxcontrib-mermaid; extra == "docs"
Provides-Extra: lint
Requires-Dist: pre-commit; extra == "lint"
Requires-Dist: mypy; extra == "lint"
Requires-Dist: types-requests; extra == "lint"
Requires-Dist: types-pytz; extra == "lint"
Requires-Dist: types-Flask; extra == "lint"
Requires-Dist: ruff; extra == "lint"
